pybigue/embedding_info.py
pybigue/metrics.py
pybigue/models.py
pybigue/sampling.py
pybigue/utils.py
pybigue/kernels/clusters.py
pybigue/kernels/random_walk.py
pybigue/kernels/transforms.py
pybigue/stan/api.py
pybigue/stan/s1_beta.stan
pybigue/stan/s1_kappa.stan
pybigue/stan/s1_kappa_beta.stan
pybigue/stan/s1_theta.stan
pybigue/stan/s1_theta_kappa.stan
pybigue/stan/s1_theta_kappa_beta.stan
pybigue-1.0.0.dist-info/licenses/LICENSE
pybigue-1.0.0.dist-info/METADATA
pybigue-1.0.0.dist-info/WHEEL
pybigue-1.0.0.dist-info/top_level.txt
pybigue-1.0.0.dist-info/RECORD
