Metadata-Version: 2.4
Name: pybigue
Version: 1.0.0
Summary: Sampling algorithm of network hyperbolic embeddings.
Author-email: Simon Lizotte <simon.lizotte.1@ulaval.ca>
License-Expression: GPL-3.0-or-later
Project-URL: Repository, https://github.com/DynamicaLab/bigue.git
Keywords: mcmc,hyperbolic,embedding,networks
Classifier: Programming Language :: Python :: 3
Requires-Python: >=3.10
License-File: LICENSE
Requires-Dist: numpy
Requires-Dist: scipy
Requires-Dist: cmdstanpy
Requires-Dist: numba
Provides-Extra: dev
Requires-Dist: pytest; extra == "dev"
Dynamic: license-file
